dirmarks/__init__.py
dirmarks/colors.py
dirmarks/data/dirmarks.function
dirmarks/main.py
dirmarks/main_original.py
dirmarks/marks_enhanced.py
dirmarks-0.1.9.dist-info/METADATA
dirmarks-0.1.9.dist-info/WHEEL
dirmarks-0.1.9.dist-info/entry_points.txt
dirmarks-0.1.9.dist-info/licenses/LICENSE
dirmarks-0.1.9.dist-info/RECORD
