Metadata-Version: 2.4
Name: dirmarks
Version: 0.1.9
Summary: Bookmarks for the filesystem
License: MIT
License-File: LICENSE
Author: Meir Michanie
Author-email: meirm@cyborg.fi
Requires-Python: >=3.9,<4.0
Classifier: License :: OSI Approved :: MIT License
Classifier: Programming Language :: Python :: 3
Classifier: Programming Language :: Python :: 3.9
Classifier: Programming Language :: Python :: 3.10
Classifier: Programming Language :: Python :: 3.11
Classifier: Programming Language :: Python :: 3.12
Classifier: Programming Language :: Python :: 3.13
Classifier: Programming Language :: Python :: 3.14
Requires-Dist: colorama (>=0.4.6,<0.5.0)
Requires-Dist: six (>=1.16.0,<2.0.0)
